[{"date":"2020-04-30","firstName":"Almar","lastName":"Teitsson","phone":"112","tourId":1,"seats":1,"bookingId":1,"email":"a@i.is"},{"date":"4\/12\/2020","firstName":"Björgvin","lastName":"Hall","phone":"1234567","tourId":11,"seats":4,"bookingId":6130,"email":"asdf@adf.is"},{"date":"4\/15\/2020","firstName":"asd","lastName":"asd","phone":"55555555","tourId":2,"seats":4,"bookingId":9838,"email":"qweqwe@fdasas.com"},{"date":"4\/15\/2020","firstName":"asd","lastName":"asd","phone":"55555555","tourId":2,"seats":4,"bookingId":2838,"email":"qweqwe@fdasas.com"},{"date":"4\/15\/2020","firstName":"a","lastName":"a","phone":"3","tourId":2,"seats":3,"bookingId":9586,"email":"e@.com"},{"date":"4\/17\/2020","firstName":"a","lastName":"a","phone":"3333","tourId":14,"seats":3,"bookingId":9372,"email":"a@.com"},{"date":"4\/17\/2020","firstName":"kiddi","lastName":"asd","phone":"333","tourId":8,"seats":3,"bookingId":6986,"email":"ka@gmail.com"},{"date":"4\/9\/2020","firstName":"sss","lastName":"qwe","phone":"23222","tourId":7,"seats":3,"bookingId":4936,"email":"k@gmail.com"},{"date":"4\/22\/2020","firstName":"s","lastName":"s","phone":"22222","tourId":9,"seats":3,"bookingId":8941,"email":"kiddi@gmail.com"},{"date":"4\/14\/2020","firstName":"a","lastName":"a","phone":"333","tourId":6,"seats":3,"bookingId":8363,"email":"a@a.is"},{"date":"4\/23\/2020","firstName":"a","lastName":"a","phone":"333","tourId":4,"seats":3,"bookingId":8610,"email":"a@a.is"},{"date":"4\/12\/2020","firstName":"a","lastName":"a","phone":"333","tourId":11,"seats":3,"bookingId":4863,"email":"a@a.is"},{"date":"4\/29\/2020","firstName":"a","lastName":"a","phone":"333","tourId":16,"seats":3,"bookingId":2258,"email":"a@a.is"},{"date":"4\/23\/2020","firstName":"a","lastName":"a","phone":"222","tourId":4,"seats":3,"bookingId":3018,"email":"a@q.is"},{"date":"4\/12\/2020","firstName":"a","lastName":"a","phone":"333","tourId":11,"seats":3,"bookingId":5263,"email":"a@a.is"},{"date":"4\/9\/2020","firstName":"a","lastName":"a","phone":"333","tourId":7,"seats":3,"bookingId":9104,"email":"a@a.os"},{"date":"4\/10\/2020","firstName":"a","lastName":"a","phone":"333","tourId":5,"seats":3,"bookingId":2330,"email":"a@a.is"},{"date":"4\/23\/2020","firstName":"a","lastName":"a","phone":"333","tourId":4,"seats":3,"bookingId":6811,"email":"a@a.is"},{"date":"4\/23\/2020","firstName":"a","lastName":"a","phone":"333","tourId":4,"seats":3,"bookingId":3323,"email":"a@a.is"}]